matrax/__init__.py
matrax/env.py
matrax/types.py
matrax/version.py
matrax/games/__init__.py
matrax/games/climbing.py
matrax/games/conflict.py
matrax/games/no_conflict.py
matrax/games/penalty.py
matrax/games/utils.py
matrax-0.0.5.dist-info/LICENSE
matrax-0.0.5.dist-info/METADATA
matrax-0.0.5.dist-info/WHEEL
matrax-0.0.5.dist-info/top_level.txt
matrax-0.0.5.dist-info/RECORD
