Metadata-Version: 2.1
Name: matrax
Version: 0.0.5
Summary: Matrix games in JAX
Home-page: https://github.com/instadeepai/matrax/
Author: InstaDeep
Author-email: a.pretorius@instadeep.com
License: Apache 2.0
Keywords: matrix-games python jax
Classifier: Development Status :: 4 - Beta
Classifier: Environment :: Console
Classifier: Intended Audience :: Science/Research
Classifier: Intended Audience :: Developers
Classifier: Operating System :: OS Independent
Classifier: Programming Language :: Python :: 3.8
Classifier: Programming Language :: Python :: 3.9
Classifier: Topic :: Scientific/Engineering :: Artificial Intelligence
Classifier: Topic :: Software Development :: Libraries :: Python Modules
Classifier: License :: OSI Approved :: Apache Software License
Requires-Python: >=3.8
License-File: LICENSE
Requires-Dist: jumanji
Provides-Extra: dev
Requires-Dist: black==22.3.0; extra == "dev"
Requires-Dist: coverage; extra == "dev"
Requires-Dist: flake8==3.9.2; extra == "dev"
Requires-Dist: importlib-metadata<5.0; extra == "dev"
Requires-Dist: isort==5.11.5; extra == "dev"
Requires-Dist: mypy==0.991; extra == "dev"
Requires-Dist: pre-commit==2.17.0; extra == "dev"
Requires-Dist: pytest==7.0.1; extra == "dev"
Requires-Dist: pytest-cov; extra == "dev"
Requires-Dist: pytest-parallel; extra == "dev"
Requires-Dist: pytest-xdist; extra == "dev"
